lrucacheNivKum-0.2.dist-info/DESCRIPTION.rst
lrucacheNivKum-0.2.dist-info/METADATA
lrucacheNivKum-0.2.dist-info/RECORD
lrucacheNivKum-0.2.dist-info/WHEEL
lrucacheNivKum-0.2.dist-info/metadata.json
lrucacheNivKum-0.2.dist-info/top_level.txt
lrucachenivkum/__init__.py
lrucachenivkum/lru.py
