Metadata-Version: 2.0
Name: lrucacheNivKum
Version: 0.2
Summary: LRU cache implementation
Home-page: https://github.com/Niveditha-kumaran/lrucachenivkum
Author: Niveditha Kumaran
Author-email: nov28niv@gmail.com
License: MIT
Platform: UNKNOWN
